RSSscpi/Instrument.py
RSSscpi/SCPI_gen_support.py
RSSscpi/SCPI_property.py
RSSscpi/SCPI_response.py
RSSscpi/SocketInterface.py
RSSscpi/ZNB.py
RSSscpi/ZVA.py
RSSscpi/__init__.py
RSSscpi/gen/ZNB_gen.py
RSSscpi/gen/ZVA_gen.py
RSSscpi/gen/__init__.py
RSSscpi-0.1.0.dev1.dist-info/DESCRIPTION.rst
RSSscpi-0.1.0.dev1.dist-info/METADATA
RSSscpi-0.1.0.dev1.dist-info/RECORD
RSSscpi-0.1.0.dev1.dist-info/WHEEL
RSSscpi-0.1.0.dev1.dist-info/metadata.json
RSSscpi-0.1.0.dev1.dist-info/top_level.txt
