Metadata-Version: 2.0
Name: RSSscpi
Version: 0.1.0.dev1
Summary: A package for controlling SCPI based instruments in a pythonic way.
Home-page: http://github.com/luksan/RSSscpi
Author: Lukas Sandström
Author-email: lukas.sandstrom@rohde-schwarz.com
License: BSD
Keywords: instrument control SCPI VISA VNA
Platform: UNKNOWN
Classifier: Development Status :: 3 - Alpha
Classifier: Intended Audience :: Developers
Classifier: License :: OSI Approved :: BSD License
Classifier: Operating System :: Unix
Classifier: Operating System :: POSIX
Classifier: Operating System :: Microsoft :: Windows
Classifier: Programming Language :: Python
Classifier: Programming Language :: Python :: 2.7
Classifier: Programming Language :: Python :: 3
Classifier: Programming Language :: Python :: 3.3
Classifier: Programming Language :: Python :: 3.4
Classifier: Programming Language :: Python :: 3.5
Classifier: Programming Language :: Python :: 3.6
Classifier: Programming Language :: Python :: Implementation :: CPython
Classifier: Programming Language :: Python :: Implementation :: PyPy
Classifier: Topic :: Software Development :: Libraries
Requires-Dist: PyVISA (>=1.8)
Requires-Dist: enum34
Provides-Extra: dev
Requires-Dist: beautifulsoup4 (>=4.5.1); extra == 'dev'
Requires-Dist: numpy (>=1.11.2); extra == 'dev'
Requires-Dist: pytest (>=3.07); extra == 'dev'
